.gitignore
.gitreview
HACKING.rst
LICENSE
MANIFEST.in
README.rst
babel.cfg
requirements.txt
run_tests.sh
setup.cfg
setup.py
test-requirements.txt
tox.ini
ardana_opsconsole_server.egg-info/PKG-INFO
ardana_opsconsole_server.egg-info/SOURCES.txt
ardana_opsconsole_server.egg-info/dependency_links.txt
ardana_opsconsole_server.egg-info/entry_points.txt
ardana_opsconsole_server.egg-info/not-zip-safe
ardana_opsconsole_server.egg-info/requires.txt
ardana_opsconsole_server.egg-info/top_level.txt
bll/__init__.py
bll/app.py
bll/hooks.py
bll/schema.sql
bll/api/__init__.py
bll/api/auth_token.py
bll/api/request.py
bll/api/response.py
bll/api/controllers/__init__.py
bll/api/controllers/app_controller.py
bll/api/controllers/root.py
bll/api/controllers/v1.py
bll/common/__init__.py
bll/common/exception.py
bll/common/i18n.py
bll/common/job_status.py
bll/common/util.py
bll/locale/messages.pot
bll/locale/en/LC_MESSAGES/messages.po
bll/locale/ja/LC_MESSAGES/messages.po
bll/locale/zh/LC_MESSAGES/messages.po
bll/plugins/__init__.py
bll/plugins/ardana_service.py
bll/plugins/baremetal_service.py
bll/plugins/catalog_service.py
bll/plugins/cinder_service.py
bll/plugins/compute_service.py
bll/plugins/eon_service.py
bll/plugins/integratedtools_service.py
bll/plugins/ironic_service.py
bll/plugins/monitor_service.py
bll/plugins/nova_service.py
bll/plugins/objectstorage_summary_service.py
bll/plugins/preferences_service.py
bll/plugins/region_client.py
bll/plugins/service.py
bll/plugins/user_group_service.py
doc/source/conf.py
doc/source/index.rst
doc/source/pluginapi.rst
doc/source/readme.rst
doc/source/restapi.rst
doc/source/services.rst
doc/source/service/ardana.rst
doc/source/service/baremetal.rst
doc/source/service/catalog.rst
doc/source/service/cinder.rst
doc/source/service/compute.rst
doc/source/service/eon.rst
doc/source/service/eula.rst
doc/source/service/integratedtools.rst
doc/source/service/ironic.rst
doc/source/service/monitor.rst
doc/source/service/nova.rst
doc/source/service/objectstorage_summary.rst
doc/source/service/preferences.rst
doc/source/service/user_group.rst
stubs/__init__.py
stubs/common/__init__.py
stubs/common/dict_job_status.py
stubs/plugins/__init__.py
stubs/plugins/composite_service.py
stubs/plugins/expose_service.py
stubs/plugins/general_service.py
stubs/plugins/setup.py
tests/__init__.py
