Metadata-Version: 1.1
Name: ardana-opsconsole-server
Version: 1.0
Summary: Business Logic Layer for the Operations Console
Home-page: https://github.com/ArdanaCLM
Author: SUSE LLC
Author-email: UNKNOWN
License: Apache-2.0
Platform: UNKNOWN
Classifier: Environment :: OpenStack
Classifier: Intended Audience :: Information Technology
Classifier: Intended Audience :: System Administrators
Classifier: License :: Other/Proprietary License
Classifier: Operating System :: POSIX :: Linux
Classifier: Programming Language :: Python
Classifier: Programming Language :: Python :: 2
Classifier: Programming Language :: Python :: 2.7
